[
    {
        "id": "V_1",
        "operation_time": 24,
        "capacity": 15,
        "gps_id": "G_1",
        "update_time": 1754537400.0,
        "cur_factory_id": "206128e3ee9a458d9cfd053cedc0fad6",
        "arrive_time_at_current_factory": 1754519087.0,
        "leave_time_at_current_factory": 1754537400.0,
        "carrying_items": [],
        "destination": null
    },
    {
        "id": "V_2",
        "operation_time": 24,
        "capacity": 15,
        "gps_id": "G_2",
        "update_time": 1754537400.0,
        "cur_factory_id": "7fe14b93f0f04ee7a994ef5b2c1fdb72",
        "arrive_time_at_current_factory": 1754499600,
        "leave_time_at_current_factory": 1754537400.0,
        "carrying_items": [],
        "destination": null
    },
    {
        "id": "V_3",
        "operation_time": 24,
        "capacity": 15,
        "gps_id": "G_3",
        "update_time": 1754537400.0,
        "cur_factory_id": "dd538f8238a5430b8135b89b8afe2511",
        "arrive_time_at_current_factory": 1754521140.0,
        "leave_time_at_current_factory": 1754537400.0,
        "carrying_items": [],
        "destination": null
    },
    {
        "id": "V_4",
        "operation_time": 24,
        "capacity": 15,
        "gps_id": "G_4",
        "update_time": 1754537400.0,
        "cur_factory_id": "e47399648fa842b2b8f80094343d8091",
        "arrive_time_at_current_factory": 1754499600,
        "leave_time_at_current_factory": 1754537400.0,
        "carrying_items": [],
        "destination": null
    },
    {
        "id": "V_5",
        "operation_time": 24,
        "capacity": 15,
        "gps_id": "G_5",
        "update_time": 1754537400.0,
        "cur_factory_id": "",
        "arrive_time_at_current_factory": 0,
        "leave_time_at_current_factory": 0,
        "carrying_items": [
            "0745420132-1",
            "0728060131-1",
            "0647140128-1",
            "0647140128-2",
            "0748340134-1"
        ],
        "destination": {
            "factory_id": "9f1a09c368584eba9e7f10a53d55caae",
            "delivery_item_list": [
                "0748340134-1",
                "0647140128-2",
                "0647140128-1"
            ],
            "pickup_item_list": [],
            "arrive_time": 1754537580.0,
            "leave_time": 1754540100.0
        }
    },
    {
        "id": "V_6",
        "operation_time": 24,
        "capacity": 15,
        "gps_id": "G_6",
        "update_time": 1754537400.0,
        "cur_factory_id": "b6dd694ae05541dba369a2a759d2c2b9",
        "arrive_time_at_current_factory": 1754535420.0,
        "leave_time_at_current_factory": 1754538540.0,
        "carrying_items": [
            "0912130152-1",
            "0919090154-1",
            "0822500145-1",
            "0822500145-2",
            "0822500145-3",
            "0822500145-4",
            "0822500145-5",
            "0822500145-6",
            "0822500145-7",
            "0822500145-8",
            "0822500145-9",
            "0928230159-1",
            "0928230159-2"
        ],
        "destination": {
            "factory_id": "ffd0ed8719f54294a452ed3e3b6a986c",
            "delivery_item_list": [],
            "pickup_item_list": [
                "0942330167-1"
            ],
            "arrive_time": 1754538576.0,
            "leave_time": 1754540616.0
        }
    },
    {
        "id": "V_7",
        "operation_time": 24,
        "capacity": 15,
        "gps_id": "G_7",
        "update_time": 1754537400.0,
        "cur_factory_id": "9b40bfd6ca1c432498685540652a5a8b",
        "arrive_time_at_current_factory": 1754537196.0,
        "leave_time_at_current_factory": 1754539356.0,
        "carrying_items": [
            "0922450155-1",
            "0924000156-1",
            "0908330150-1",
            "0940070166-1",
            "0807160142-1"
        ],
        "destination": {
            "factory_id": "5e2e9efa5ade4984bb18af66028bc0c8",
            "delivery_item_list": [
                "0807160142-1",
                "0940070166-1",
                "0908330150-1"
            ],
            "pickup_item_list": [
                "1004070176-1",
                "0956240174-1"
            ],
            "arrive_time": 1754541432.0,
            "leave_time": 1754543772.0
        }
    },
    {
        "id": "V_8",
        "operation_time": 24,
        "capacity": 15,
        "gps_id": "G_8",
        "update_time": 1754537400.0,
        "cur_factory_id": "",
        "arrive_time_at_current_factory": 0,
        "leave_time_at_current_factory": 0,
        "carrying_items": [],
        "destination": {
            "factory_id": "5920212e6b0b46b198b9677bfe74f35d",
            "delivery_item_list": [],
            "pickup_item_list": [
                "0924070157-1"
            ],
            "arrive_time": 1754537700.0,
            "leave_time": 1754539620.0
        }
    },
    {
        "id": "V_9",
        "operation_time": 24,
        "capacity": 15,
        "gps_id": "G_9",
        "update_time": 1754537400.0,
        "cur_factory_id": "b6dd694ae05541dba369a2a759d2c2b9",
        "arrive_time_at_current_factory": 1754534628.0,
        "leave_time_at_current_factory": 1754537400.0,
        "carrying_items": [],
        "destination": null
    },
    {
        "id": "V_10",
        "operation_time": 24,
        "capacity": 15,
        "gps_id": "G_10",
        "update_time": 1754537400.0,
        "cur_factory_id": "",
        "arrive_time_at_current_factory": 0,
        "leave_time_at_current_factory": 0,
        "carrying_items": [],
        "destination": {
            "factory_id": "5920212e6b0b46b198b9677bfe74f35d",
            "delivery_item_list": [],
            "pickup_item_list": [
                "0958400175-19",
                "0958400175-20",
                "0958400175-21",
                "0958400175-22",
                "0958400175-23",
                "0958400175-24",
                "0953000172-1"
            ],
            "arrive_time": 1754539512.0,
            "leave_time": 1754542092.0
        }
    },
    {
        "id": "V_11",
        "operation_time": 24,
        "capacity": 15,
        "gps_id": "G_11",
        "update_time": 1754537400.0,
        "cur_factory_id": "4a85fbdd319140dd83f55766289d365f",
        "arrive_time_at_current_factory": 1754499600,
        "leave_time_at_current_factory": 1754537400.0,
        "carrying_items": [],
        "destination": null
    },
    {
        "id": "V_12",
        "operation_time": 24,
        "capacity": 15,
        "gps_id": "G_12",
        "update_time": 1754537400.0,
        "cur_factory_id": "",
        "arrive_time_at_current_factory": 0,
        "leave_time_at_current_factory": 0,
        "carrying_items": [],
        "destination": {
            "factory_id": "2445d4bd004c457d95957d6ecf77f759",
            "delivery_item_list": [],
            "pickup_item_list": [
                "0932500163-1",
                "0932370162-1",
                "0932370162-2",
                "0931260161-1",
                "0908390151-1",
                "0908390151-2",
                "0908390151-3",
                "0949450170-1",
                "0949450170-2",
                "0949450170-3",
                "0949450170-4",
                "0903440146-1"
            ],
            "arrive_time": 1754537544.0,
            "leave_time": 1754541204.0
        }
    },
    {
        "id": "V_13",
        "operation_time": 24,
        "capacity": 15,
        "gps_id": "G_13",
        "update_time": 1754537400.0,
        "cur_factory_id": "9f1a09c368584eba9e7f10a53d55caae",
        "arrive_time_at_current_factory": 1754537220.0,
        "leave_time_at_current_factory": 1754539080.0,
        "carrying_items": [],
        "destination": null
    },
    {
        "id": "V_14",
        "operation_time": 24,
        "capacity": 15,
        "gps_id": "G_14",
        "update_time": 1754537400.0,
        "cur_factory_id": "",
        "arrive_time_at_current_factory": 0,
        "leave_time_at_current_factory": 0,
        "carrying_items": [],
        "destination": {
            "factory_id": "5920212e6b0b46b198b9677bfe74f35d",
            "delivery_item_list": [],
            "pickup_item_list": [
                "0958400175-1",
                "0958400175-2",
                "0958400175-3",
                "0958400175-4",
                "0958400175-5",
                "0958400175-6",
                "0958400175-7",
                "0958400175-8",
                "0958400175-9",
                "0958400175-10",
                "0958400175-11",
                "0958400175-12",
                "0958400175-13",
                "0958400175-14",
                "0958400175-15",
                "0958400175-16",
                "0958400175-17",
                "0958400175-18"
            ],
            "arrive_time": 1754539500.0,
            "leave_time": 1754544900.0
        }
    },
    {
        "id": "V_15",
        "operation_time": 24,
        "capacity": 15,
        "gps_id": "G_15",
        "update_time": 1754537400.0,
        "cur_factory_id": "",
        "arrive_time_at_current_factory": 0,
        "leave_time_at_current_factory": 0,
        "carrying_items": [
            "0752490135-1",
            "0804500140-1",
            "0758250138-1"
        ],
        "destination": {
            "factory_id": "b6dd694ae05541dba369a2a759d2c2b9",
            "delivery_item_list": [
                "0758250138-1"
            ],
            "pickup_item_list": [],
            "arrive_time": 1754537424.0,
            "leave_time": 1754539344.0
        }
    },
    {
        "id": "V_16",
        "operation_time": 24,
        "capacity": 15,
        "gps_id": "G_16",
        "update_time": 1754537400.0,
        "cur_factory_id": "5e2e9efa5ade4984bb18af66028bc0c8",
        "arrive_time_at_current_factory": 1754536800.0,
        "leave_time_at_current_factory": 1754539080.0,
        "carrying_items": [
            "1014070178-1",
            "1014070178-2"
        ],
        "destination": {
            "factory_id": "2445d4bd004c457d95957d6ecf77f759",
            "delivery_item_list": [],
            "pickup_item_list": [
                "1019320180-1",
                "0925310158-1",
                "0931260160-1",
                "0949330169-1",
                "0934570164-1"
            ],
            "arrive_time": 1754540136.0,
            "leave_time": 1754542776.0
        }
    },
    {
        "id": "V_17",
        "operation_time": 24,
        "capacity": 15,
        "gps_id": "G_17",
        "update_time": 1754537400.0,
        "cur_factory_id": "206128e3ee9a458d9cfd053cedc0fad6",
        "arrive_time_at_current_factory": 1754534412.0,
        "leave_time_at_current_factory": 1754539452.0,
        "carrying_items": [],
        "destination": null
    },
    {
        "id": "V_18",
        "operation_time": 24,
        "capacity": 15,
        "gps_id": "G_18",
        "update_time": 1754537400.0,
        "cur_factory_id": "6ac617af0ea04e9bbbc3b206d86d73a6",
        "arrive_time_at_current_factory": 1754521968.0,
        "leave_time_at_current_factory": 1754537400.0,
        "carrying_items": [],
        "destination": null
    },
    {
        "id": "V_19",
        "operation_time": 24,
        "capacity": 15,
        "gps_id": "G_19",
        "update_time": 1754537400.0,
        "cur_factory_id": "",
        "arrive_time_at_current_factory": 0,
        "leave_time_at_current_factory": 0,
        "carrying_items": [
            "0906090147-1",
            "0906440148-1"
        ],
        "destination": {
            "factory_id": "d1f8de642d734931be957336196d996d",
            "delivery_item_list": [],
            "pickup_item_list": [
                "0907270149-1",
                "1004210177-1"
            ],
            "arrive_time": 1754538084.0,
            "leave_time": 1754540244.0
        }
    },
    {
        "id": "V_20",
        "operation_time": 24,
        "capacity": 15,
        "gps_id": "G_20",
        "update_time": 1754537400.0,
        "cur_factory_id": "206128e3ee9a458d9cfd053cedc0fad6",
        "arrive_time_at_current_factory": 1754536800.0,
        "leave_time_at_current_factory": 1754539680.0,
        "carrying_items": [],
        "destination": null
    }
]